timelogging/__init__.py
timelogging/dayLog.py
timelogging/dayLogLater.py
timelogging/timeLog.py
timelogging/timeLogLater.py
timelogging-2.3.0.dist-info/LICENSE.txt
timelogging-2.3.0.dist-info/METADATA
timelogging-2.3.0.dist-info/WHEEL
timelogging-2.3.0.dist-info/top_level.txt
timelogging-2.3.0.dist-info/RECORD
