Metadata-Version: 2.1
Name: timelogging
Version: 2.3.0
Summary: Small Logging Library
Home-page: https://github.com/tbrodbeck/timelogging
Author: Tillmann Brodbeck
Author-email: t.b@riseup.net
License: UNKNOWN
Platform: UNKNOWN
Classifier: Programming Language :: Python :: 3
Classifier: License :: OSI Approved :: MIT License
Classifier: Operating System :: OS Independent
Requires-Python: >=3.6
